ha_mqtt_discoverable/__init__.py
ha_mqtt_discoverable/sensors.py
ha_mqtt_discoverable/utils.py
ha_mqtt_discoverable-0.23.0.dist-info/METADATA
ha_mqtt_discoverable-0.23.0.dist-info/WHEEL
ha_mqtt_discoverable-0.23.0.dist-info/licenses/LICENSE
ha_mqtt_discoverable-0.23.0.dist-info/RECORD
