Metadata-Version: 2.4
Name: ha-mqtt-discoverable
Version: 0.23.0
Summary: Python library for creating MQTT entities compatible with Home Assistant
License-File: LICENSE
Author: Joe Block
Author-email: jpb@unixorn.net
Requires-Python: >=3.10.0,<4.0
Classifier: Programming Language :: Python :: 3
Classifier: Programming Language :: Python :: 3.10
Classifier: Programming Language :: Python :: 3.11
Classifier: Programming Language :: Python :: 3.12
Classifier: Programming Language :: Python :: 3.13
Classifier: Programming Language :: Python :: 3.14
Requires-Dist: paho-mqtt (==2.1.0)
Requires-Dist: pydantic (==2.12.4)
